harrytsz_str2date/__init__.py
harrytsz_str2date/harrytsz_str2date.py
harrytsz_str2date-0.0.2.dist-info/LICENSE.txt
harrytsz_str2date-0.0.2.dist-info/METADATA
harrytsz_str2date-0.0.2.dist-info/WHEEL
harrytsz_str2date-0.0.2.dist-info/top_level.txt
harrytsz_str2date-0.0.2.dist-info/RECORD
